freder/__init__.py
freder/fredapi/__init__.py
freder/fredapi/api/__init__.py
freder/fredapi/api/api.py
freder/fredapi/endpoints/__init__.py
freder/fredapi/endpoints/categories.py
freder/fredapi/endpoints/endpoints.py
freder/fredapi/endpoints/releases.py
freder/fredapi/endpoints/series.py
freder/fredapi/endpoints/sources.py
freder/fredapi/endpoints/tags.py
freder/fredapi/exceptions/__init__.py
freder/fredapi/exceptions/api_exceptions.py
freder/fredapi/exceptions/common.py
freder/fredapi/params/__init__.py
freder/fredapi/params/exception.py
freder/fredapi/params/params.py
freder/fredapi/params/tools.py
freder/fredapi/params/vars.py
freder-0.0.3.dist-info/licenses/LICENSE.txt
freder-0.0.3.dist-info/WHEEL
freder-0.0.3.dist-info/METADATA
freder-0.0.3.dist-info/RECORD
